README.md
setup.cfg
setup.py
cliente/__init__.py
cliente/exceptions.py
cliente/oab.py
cliente/processo.py
cliente/tribunal.py
cliente_andamentos.egg-info/PKG-INFO
cliente_andamentos.egg-info/SOURCES.txt
cliente_andamentos.egg-info/dependency_links.txt
cliente_andamentos.egg-info/requires.txt
cliente_andamentos.egg-info/top_level.txt