Metadata-Version: 1.1
Name: cliente-andamentos
Version: 0.6.0
Summary: Cliente python para o sistema Andamentos
Home-page: https://gitlab.com/sijnet/cliente-andamentos
Author: Lucas Almeida Aguiar
Author-email: lucas.tamoios@gmail.com
License: UNKNOWN
Keywords: api andamentos processos justica
Platform: UNKNOWN
Classifier: Development Status :: 3 - Alpha
Classifier: Intended Audience :: Developers
Classifier: Topic :: Software Development :: Build Tools
Classifier: Programming Language :: Python :: 2
Classifier: Programming Language :: Python :: 2.7
Classifier: Programming Language :: Python :: 3
Classifier: Programming Language :: Python :: 3.5
